mockTest/__init__.py
mockTest/mockTest.py
mockTestAPI-0.0.5.dist-info/LICENCE
mockTestAPI-0.0.5.dist-info/METADATA
mockTestAPI-0.0.5.dist-info/WHEEL
mockTestAPI-0.0.5.dist-info/top_level.txt
mockTestAPI-0.0.5.dist-info/RECORD
